demv/__init__.py
demv/demv.py
demv/helpers.py
demv-1.0.2.dist-info/LICENSE
demv-1.0.2.dist-info/METADATA
demv-1.0.2.dist-info/WHEEL
demv-1.0.2.dist-info/top_level.txt
demv-1.0.2.dist-info/RECORD
