Metadata-Version: 2.1
Name: demv
Version: 1.0.2
Summary: Debiaser for Multiple Variables(DEMV) is a pre-processing algorithm for binary and multi-class datasets that mitigates bias by perfectly balancing the sensitive groups identified by each possible sensitive variables' value and each label's value
Author-email: Giordano d'Aloisio <giordano.daloisio@gmail.com>
License: GNU AFFERO GENERAL PUBLIC LICENSE
Project-URL: Homepage, https://github.com/giordanoDaloisio/demv
Keywords: bias,fairness,preprocessing,classification,multi class
Classifier: License :: OSI Approved :: GNU Affero General Public License v3
Classifier: Programming Language :: Python
Classifier: Programming Language :: Python :: 3
Requires-Python: >=3.6.0
License-File: LICENSE
Requires-Dist: pandas
Requires-Dist: numpy
Requires-Dist: scikit-learn
Provides-Extra: dev
Requires-Dist: pytest ; extra == 'dev'
